small_calc/__init__.py
small_calc/small_calc.py
small_calc-0.0.1.dist-info/METADATA
small_calc-0.0.1.dist-info/WHEEL
small_calc-0.0.1.dist-info/top_level.txt
small_calc-0.0.1.dist-info/RECORD
