Metadata-Version: 2.1
Name: small-calc
Version: 0.0.1
Summary: Testing the creation of packages in Pypi with a small calculator package
Home-page: https://github.com/on-ferreira/simple-package-test
Author: Orlando Nascimento
Author-email: on_ferreira@id.uff.br
Requires-Python: >=3.8
